syft_wallet/__init__.py
syft_wallet/cli.py
syft_wallet/py.typed
syft_wallet-0.1.1.dist-info/METADATA
syft_wallet-0.1.1.dist-info/WHEEL
syft_wallet-0.1.1.dist-info/entry_points.txt
syft_wallet-0.1.1.dist-info/licenses/LICENSE
syft_wallet-0.1.1.dist-info/RECORD
