Metadata-Version: 2.4
Name: syft-wallet
Version: 0.1.1
Summary: Secure key and secret management for SyftBox using 1Password integration
Project-URL: Homepage, https://github.com/OpenMined/SyftWallet
Project-URL: Documentation, https://github.com/OpenMined/SyftWallet#readme
Project-URL: Repository, https://github.com/OpenMined/SyftWallet.git
Project-URL: Issues, https://github.com/OpenMined/SyftWallet/issues
Project-URL: Changelog, https://github.com/OpenMined/SyftWallet/releases
Author-email: OpenMined <info@openmined.org>
Maintainer-email: OpenMined <info@openmined.org>
License-Expression: Apache-2.0
License-File: LICENSE
Keywords: 1password,keyring,privacy,secrets,security,syft,wallet
Classifier: Development Status :: 4 - Beta
Classifier: Intended Audience :: Developers
Classifier: License :: OSI Approved :: Apache Software License
Classifier: Operating System :: OS Independent
Classifier: Programming Language :: Python :: 3
Classifier: Programming Language :: Python :: 3.10
Classifier: Programming Language :: Python :: 3.11
Classifier: Programming Language :: Python :: 3.12
Classifier: Topic :: Security
Classifier: Topic :: Security :: Cryptography
Classifier: Topic :: Software Development :: Libraries :: Python Modules
Classifier: Topic :: System :: Systems Administration
Requires-Python: >=3.10
Requires-Dist: click>=8.0.0
Requires-Dist: cryptography>=41.0.0
Requires-Dist: keyring>=24.0.0
Requires-Dist: pydantic>=2.0.0
Requires-Dist: python-dotenv>=1.0.0
Requires-Dist: rich>=13.0.0
Provides-Extra: dev
Requires-Dist: black>=23.0.0; extra == 'dev'
Requires-Dist: flake8>=6.0.0; extra == 'dev'
Requires-Dist: isort>=5.0.0; extra == 'dev'
Requires-Dist: mypy>=1.0.0; extra == 'dev'
Requires-Dist: pytest-cov>=4.0.0; extra == 'dev'
Requires-Dist: pytest>=7.0.0; extra == 'dev'
Provides-Extra: jupyter
Requires-Dist: ipython>=8.0.0; extra == 'jupyter'
Requires-Dist: ipywidgets>=8.0.0; extra == 'jupyter'
